{"subItptOf":"O9nLtF3b4","canInterpretType":"try/low-code/editor-ObjectType","nameSelf":"try/low-code/editor","ownKVLs":[{"key":"InterpreterReferenceMapKey","value":{"O9nLtF3b4":{"subItptOf":"metaexplorer.io/baseContainer","canInterpretType":"metaexplorer.io/ContainerObjType","nameSelf":"O9nLtF3b4","ownKVLs":[{"key":"in_0","value":{"objRef":"KSdHDrbac","propRef":null},"ldType":"InterpreterClassType"}],"crudSkills":"cRud","inKeys":["in_0"]},"KSdHDrbac":{"subItptOf":"metaexplorer.io/layout/CSSWrapper","canInterpretType":"metaexplorer.io/layout/CSSWrapper-ObjectType","nameSelf":"KSdHDrbac","ownKVLs":[{"key":"inputContainer","value":{"objRef":"NI8g_Nqxw","propRef":null},"ldType":"InterpreterClassType"}],"crudSkills":"cRud","inKeys":["inputContainer"]},"NI8g_Nqxw":{"subItptOf":"metaexplorer.io/block-editor","canInterpretType":"blockeditortype","nameSelf":"NI8g_Nqxw","ownKVLs":[{"key":"currentlyediting","value":"landing/google-using-structured-data/mailto-form","ldType":"http://schema.org/Text"},{"key":"isFullScreenPreview","value":false,"ldType":"http://schema.org/Boolean"},{"key":"hiddenViews","value":"preview","ldType":"http://schema.org/Text"},{"key":"hiddenViews","value":"drawer","ldType":"http://schema.org/Text"}],"crudSkills":"cRud","inKeys":[]}},"ldType":"InterpreterReferenceMapType"}],"crudSkills":"cRud","inKeys":[]}