{"subItptOf":"26aa2efe-db2d-44ee-bb76-e2706c812069","canInterpretType":"metaexplorer.io/tinyentrepreneur/income-record-form-ObjectType","nameSelf":"metaexplorer.io/tinyentrepreneur/income-record-form","ownKVLs":[{"key":"InterpreterReferenceMapKey","value":{"26aa2efe-db2d-44ee-bb76-e2706c812069":{"subItptOf":"metaexplorer.io/material-design/NavProcessAtom","canInterpretType":"metaexplorer.io/material-design/NavProcessAtom-ObjectType","nameSelf":"26aa2efe-db2d-44ee-bb76-e2706c812069","ownKVLs":[{"key":"inputContainer","value":{"objRef":"32b677cb-ce47-4bb6-a58d-6498c6c08149","propRef":null},"ldType":"InterpreterClassType"},{"key":"HeaderText","value":"new income record","ldType":"http://schema.org/Text"},{"key":"confirmTxt","value":"save","ldType":"http://schema.org/Text"},{"key":"RouteSend_cancel","value":"../","ldType":"Route_Added"},{"key":"RouteSend_confirm","value":"../","ldType":"Route_Added"}],"crudSkills":"cRud","inKeys":["inputContainer"]},"32b677cb-ce47-4bb6-a58d-6498c6c08149":{"subItptOf":"metaexplorer.io/layout/vh-centered-column","canInterpretType":"metaexplorer.io/layout/vh-centered-column-ObjectType","nameSelf":"32b677cb-ce47-4bb6-a58d-6498c6c08149","ownKVLs":[{"key":"inputContainer","value":{"objRef":"9379bf06-6563-4bdd-8c07-527a1fb2038b","propRef":null},"ldType":"InterpreterClassType"}],"crudSkills":"cRud","inKeys":["inputContainer"]},"9379bf06-6563-4bdd-8c07-527a1fb2038b":{"subItptOf":"metaexplorer.io/baseContainer","canInterpretType":"metaexplorer.io/ContainerObjType","nameSelf":"9379bf06-6563-4bdd-8c07-527a1fb2038b","ownKVLs":[{"key":"in_0","value":{"objRef":"e8016df1-1a7f-4fad-aa1e-1138cda392d5","propRef":null},"ldType":"InterpreterClassType"},{"key":"in_1","value":{"objRef":"6255886a-5226-42aa-a9db-4bf21e76be04","propRef":null},"ldType":"InterpreterClassType"},{"key":"in_2","value":{"objRef":"b644c4ad-dcd2-48a1-ac9b-09ec55ea381f","propRef":null},"ldType":"InterpreterClassType"},{"key":"in_3","value":{"objRef":"64d00460-f088-46c7-87c4-8fd7dd6b63d5","propRef":null},"ldType":"InterpreterClassType"}],"crudSkills":"cRud","inKeys":["in_0","in_1","in_2","in_3"]},"e8016df1-1a7f-4fad-aa1e-1138cda392d5":{"subItptOf":"metaexplorer.io/material-design/SingleImageSelector","canInterpretType":"http://schema.org/CreateAction","nameSelf":"e8016df1-1a7f-4fad-aa1e-1138cda392d5","ownKVLs":[],"crudSkills":"cRud","inKeys":[]},"6255886a-5226-42aa-a9db-4bf21e76be04":{"subItptOf":"metaexplorer.io/material-design/http://schema.org/Number","canInterpretType":"http://schema.org/Number","nameSelf":"6255886a-5226-42aa-a9db-4bf21e76be04","ownKVLs":[{"key":"http://schema.org/description","value":"Total amount (in €)","ldType":"http://schema.org/Text"}],"crudSkills":"cRud","inKeys":[]},"b644c4ad-dcd2-48a1-ac9b-09ec55ea381f":{"subItptOf":"metaexplorer.io/material-design/http://schema.org/Text","canInterpretType":"http://schema.org/Text","nameSelf":"b644c4ad-dcd2-48a1-ac9b-09ec55ea381f","ownKVLs":[{"key":"http://schema.org/description","value":"What's it for?","ldType":"http://schema.org/Text"},{"key":"inputdata","value":"","ldType":"http://schema.org/Text"}],"crudSkills":"cRud","inKeys":[]},"64d00460-f088-46c7-87c4-8fd7dd6b63d5":{"subItptOf":"metaexplorer.io/material-design/http://schema.org/Date","canInterpretType":"http://schema.org/Date","nameSelf":"64d00460-f088-46c7-87c4-8fd7dd6b63d5","ownKVLs":[{"key":"http://schema.org/description","value":"Date billed","ldType":"http://schema.org/Text"}],"crudSkills":"cRud","inKeys":[]}},"ldType":"InterpreterReferenceMapType"}],"crudSkills":"cRud","inKeys":[]}